<?xml version="1.0" encoding="utf-8" ?>
<dwsync>
<file name="block_address.png" server="ftp.edmultimedia.net//chalenger/" local="128779154640000000" remote="128899786200000000" />
<file name="block_blockquote.png" server="ftp.edmultimedia.net//chalenger/" local="128779154640000000" remote="128899786200000000" />
<file name="block_div.png" server="ftp.edmultimedia.net//chalenger/" local="128779154640000000" remote="128899786200000000" />
<file name="block_h1.png" server="ftp.edmultimedia.net//chalenger/" local="128779154640000000" remote="128899786800000000" />
<file name="block_h2.png" server="ftp.edmultimedia.net//chalenger/" local="128779154640000000" remote="128899786800000000" />
<file name="block_h3.png" server="ftp.edmultimedia.net//chalenger/" local="128779154640000000" remote="128899786800000000" />
<file name="block_h4.png" server="ftp.edmultimedia.net//chalenger/" local="128779154640000000" remote="128899786800000000" />
<file name="block_h5.png" server="ftp.edmultimedia.net//chalenger/" local="128779154640000000" remote="128899786800000000" />
<file name="block_h6.png" server="ftp.edmultimedia.net//chalenger/" local="128779154640000000" remote="128899786800000000" />
<file name="block_p.png" server="ftp.edmultimedia.net//chalenger/" local="128779154640000000" remote="128899786800000000" />
<file name="block_pre.png" server="ftp.edmultimedia.net//chalenger/" local="128779154640000000" remote="128899786800000000" />
<file name="fck_anchor.gif" server="ftp.edmultimedia.net//chalenger/" local="128779154640000000" remote="128899786800000000" />
<file name="fck_flashlogo.gif" server="ftp.edmultimedia.net//chalenger/" local="128779154640000000" remote="128899786800000000" />
<file name="fck_hiddenfield.gif" server="ftp.edmultimedia.net//chalenger/" local="128779154640000000" remote="128899786800000000" />
<file name="fck_pagebreak.gif" server="ftp.edmultimedia.net//chalenger/" local="128779154640000000" remote="128899786800000000" />
<file name="fck_plugin.gif" server="ftp.edmultimedia.net//chalenger/" local="128779154640000000" remote="128899786800000000" />
<file name="block_address.png" server="C:/wamp/www/chalenger/" local="128779154640000000" remote="128779154640000000" />
<file name="block_blockquote.png" server="C:/wamp/www/chalenger/" local="128779154640000000" remote="128779154640000000" />
<file name="block_div.png" server="C:/wamp/www/chalenger/" local="128779154640000000" remote="128779154640000000" />
<file name="block_h1.png" server="C:/wamp/www/chalenger/" local="128779154640000000" remote="128779154640000000" />
<file name="block_h2.png" server="C:/wamp/www/chalenger/" local="128779154640000000" remote="128779154640000000" />
<file name="block_h3.png" server="C:/wamp/www/chalenger/" local="128779154640000000" remote="128779154640000000" />
<file name="block_h4.png" server="C:/wamp/www/chalenger/" local="128779154640000000" remote="128779154640000000" />
<file name="block_h5.png" server="C:/wamp/www/chalenger/" local="128779154640000000" remote="128779154640000000" />
<file name="block_h6.png" server="C:/wamp/www/chalenger/" local="128779154640000000" remote="128779154640000000" />
<file name="block_p.png" server="C:/wamp/www/chalenger/" local="128779154640000000" remote="128779154640000000" />
<file name="block_pre.png" server="C:/wamp/www/chalenger/" local="128779154640000000" remote="128779154640000000" />
<file name="fck_anchor.gif" server="C:/wamp/www/chalenger/" local="128779154640000000" remote="128779154640000000" />
<file name="fck_flashlogo.gif" server="C:/wamp/www/chalenger/" local="128779154640000000" remote="128779154640000000" />
<file name="fck_hiddenfield.gif" server="C:/wamp/www/chalenger/" local="128779154640000000" remote="128779154640000000" />
<file name="fck_pagebreak.gif" server="C:/wamp/www/chalenger/" local="128779154640000000" remote="128779154640000000" />
<file name="fck_plugin.gif" server="C:/wamp/www/chalenger/" local="128779154640000000" remote="128779154640000000" />
<file name="block_address.png" server="C:/wamp/www/turismo/" local="128779154640000000" remote="128779154640000000" />
<file name="block_blockquote.png" server="C:/wamp/www/turismo/" local="128779154640000000" remote="128779154640000000" />
<file name="block_div.png" server="C:/wamp/www/turismo/" local="128779154640000000" remote="128779154640000000" />
<file name="block_h1.png" server="C:/wamp/www/turismo/" local="128779154640000000" remote="128779154640000000" />
<file name="block_h2.png" server="C:/wamp/www/turismo/" local="128779154640000000" remote="128779154640000000" />
<file name="block_h3.png" server="C:/wamp/www/turismo/" local="128779154640000000" remote="128779154640000000" />
<file name="block_h4.png" server="C:/wamp/www/turismo/" local="128779154640000000" remote="128779154640000000" />
<file name="block_h5.png" server="C:/wamp/www/turismo/" local="128779154640000000" remote="128779154640000000" />
<file name="block_h6.png" server="C:/wamp/www/turismo/" local="128779154640000000" remote="128779154640000000" />
<file name="block_p.png" server="C:/wamp/www/turismo/" local="128779154640000000" remote="128779154640000000" />
<file name="block_pre.png" server="C:/wamp/www/turismo/" local="128779154640000000" remote="128779154640000000" />
<file name="fck_anchor.gif" server="C:/wamp/www/turismo/" local="128779154640000000" remote="128779154640000000" />
<file name="fck_flashlogo.gif" server="C:/wamp/www/turismo/" local="128779154640000000" remote="128779154640000000" />
<file name="fck_hiddenfield.gif" server="C:/wamp/www/turismo/" local="128779154640000000" remote="128779154640000000" />
<file name="fck_pagebreak.gif" server="C:/wamp/www/turismo/" local="128779154640000000" remote="128779154640000000" />
<file name="fck_plugin.gif" server="C:/wamp/www/turismo/" local="128779154640000000" remote="128779154640000000" />
</dwsync>